Shell13Wen/README.md
Shell13Wen/__init__.py
Shell13Wen/__main__.py
Shell13Wen/file.epub
Shell13Wen/index.html
Shell13Wen/css/__init__.py
Shell13Wen/css/annotations.css
Shell13Wen/css/main.css
Shell13Wen/css/normalize.css
Shell13Wen/css/popup.css
Shell13Wen/font/__init__.py
Shell13Wen/font/fontello.eot
Shell13Wen/font/fontello.svg
Shell13Wen/font/fontello.ttf
Shell13Wen/font/fontello.woff
Shell13Wen/img/__init__.py
Shell13Wen/img/annotator-glyph-sprite.png
Shell13Wen/img/annotator-icon-sprite.png
Shell13Wen/img/apple-touch-icon.png
Shell13Wen/img/cancelfullscreen.png
Shell13Wen/img/close.png
Shell13Wen/img/fullscreen.png
Shell13Wen/img/loader.gif
Shell13Wen/img/menu-icon.png
Shell13Wen/img/save.png
Shell13Wen/img/saved.png
Shell13Wen/img/settings-s.png
Shell13Wen/img/settings.png
Shell13Wen/img/star.png
Shell13Wen/js/__init__.py
Shell13Wen/js/epub.js
Shell13Wen/js/epub.min.js
Shell13Wen/js/epub.min.map
Shell13Wen/js/hooks.min.js
Shell13Wen/js/hooks.min.map
Shell13Wen/js/reader.js
Shell13Wen/js/reader.js.map
Shell13Wen/js/reader.min.js
Shell13Wen/js/reader.min.map
Shell13Wen/js/hooks/__init__.py
Shell13Wen/js/hooks/extensions/__init__.py
Shell13Wen/js/hooks/extensions/highlight.js
Shell13Wen/js/libs/__init__.py
Shell13Wen/js/libs/jquery.min.js
Shell13Wen/js/libs/localforage.min.js
Shell13Wen/js/libs/screenfull.js
Shell13Wen/js/libs/screenfull.min.js
Shell13Wen/js/libs/zip.min.js
Shell13Wen/js/plugins/__init__.py
Shell13Wen/js/plugins/hypothesis.js
Shell13Wen/js/plugins/search.js
shell_13_wen-2024.3.2.0.dist-info/METADATA
shell_13_wen-2024.3.2.0.dist-info/WHEEL
shell_13_wen-2024.3.2.0.dist-info/entry_points.txt
shell_13_wen-2024.3.2.0.dist-info/top_level.txt
shell_13_wen-2024.3.2.0.dist-info/RECORD
